sensirion_uart_scc1/__init__.py
sensirion_uart_scc1/drivers/__init__.py
sensirion_uart_scc1/drivers/scc1_slf3x.py
sensirion_uart_scc1/drivers/slf_common.py
sensirion_uart_scc1/protocols/__init__.py
sensirion_uart_scc1/protocols/i2c_transceiver.py
sensirion_uart_scc1/protocols/shdlc_transceiver.py
sensirion_uart_scc1/scc1_exceptions.py
sensirion_uart_scc1/scc1_i2c_transceiver.py
sensirion_uart_scc1/scc1_shdlc_device.py
sensirion_uart_scc1-1.1.1.dist-info/LICENSE
sensirion_uart_scc1-1.1.1.dist-info/METADATA
sensirion_uart_scc1-1.1.1.dist-info/WHEEL
sensirion_uart_scc1-1.1.1.dist-info/RECORD
