Metadata-Version: 2.1
Name: sensirion-uart-scc1
Version: 1.1.1
Summary: Driver for Sensirion SCC1 USB cable
License: BSD-3-Clause
Author: Pascal Sachs
Requires-Python: >=3.8.1,<4
Classifier: License :: OSI Approved :: BSD License
Classifier: Programming Language :: Python :: 3
Classifier: Programming Language :: Python :: 3.9
Classifier: Programming Language :: Python :: 3.10
Classifier: Programming Language :: Python :: 3.11
Classifier: Programming Language :: Python :: 3.12
Requires-Dist: packaging (>=23-2,<24)
Requires-Dist: sensirion-i2c-driver (>=1.0.0,<2.0.0)
Requires-Dist: sensirion-shdlc-driver (>=0.1.5,<0.2.0)
